little_termite/__init__.py
little_termite/__main__.py
havsalt_little_termite-0.1.3.dist-info/licenses/LICENSE
havsalt_little_termite-0.1.3.dist-info/WHEEL
havsalt_little_termite-0.1.3.dist-info/entry_points.txt
havsalt_little_termite-0.1.3.dist-info/METADATA
havsalt_little_termite-0.1.3.dist-info/RECORD
