Metadata-Version: 2.4
Name: havsalt-little-termite
Version: 0.1.3
Summary: Terminate command output, by controlling this little hungry and human-looking termite
Author: Havsalt
Author-email: Havsalt <77575424+Havsalt@users.noreply.github.com>
License-Expression: MIT
License-File: LICENSE
Requires-Dist: charz[keyboard]~=0.1.0
Requires-Dist: charz-rust>=0.2.0
Requires-Python: >=3.13
